pyftg_sound/sound_manager.py
pyftg_sound/models/audio_buffer.py
pyftg_sound/models/audio_source.py
pyftg_sound/models/sound_renderer.py
pyftg_sound/openal/__init__.py
pyftg_sound/openal/al.py
pyftg_sound/openal/alc.py
pyftg_sound/openal/log.py
pyftg_sound/openal/soft.py
pyftg_sound/utils/dtype.py
pyftg_sound/utils/openal.py
pyftg_sound/utils/wave.py
pyftg_sound-0.3.dist-info/METADATA
pyftg_sound-0.3.dist-info/WHEEL
pyftg_sound-0.3.dist-info/top_level.txt
pyftg_sound-0.3.dist-info/RECORD
