Metadata-Version: 2.2
Name: pyftg-sound
Version: 0.3
Summary: A sound library for DareFightingICE with OpenAL backend
Author: TeamFightingICE
Project-URL: Homepage, https://github.com/TeamFightingICE/pyftg-sound
Project-URL: Issues, https://github.com/TeamFightingICE/pyftg-sound/issues
Classifier: Programming Language :: Python :: 3
Classifier: License :: OSI Approved :: MIT License
Classifier: Operating System :: OS Independent
Requires-Python: >=3.10
Requires-Dist: numpy~=1.26.4
